README.md
setup.py
myanalyse/__init__.py
myanalyse/ana.py
myanalyse/cbond.py
myanalyse/cncode.py
myanalyse/cnstock.py
myanalyse/download.py
myanalyse/hkcode.py
myanalyse/info.py
myanalyse/pehkipo.py
myanalyse/vix.py
myanalyse.egg-info/PKG-INFO
myanalyse.egg-info/SOURCES.txt
myanalyse.egg-info/dependency_links.txt
myanalyse.egg-info/top_level.txt
myanalyse/data/__init__.py
myanalyse/data/writedata.py