Metadata-Version: 1.2
Name: myanalyse
Version: 0.1
Summary: analyse stock
Home-page: UNKNOWN
Author: pengsir
Author-email: qq@qq.com
Maintainer: pengsir
Maintainer-email: qq@qq.com
License: BSD License
Platform: all
Classifier: Operating System :: OS Independent
Classifier: Intended Audience :: Developers
Classifier: License :: OSI Approved :: BSD License
Classifier: Programming Language :: Python
Classifier: Programming Language :: Python :: Implementation
Classifier: Programming Language :: Python :: 2
Classifier: Programming Language :: Python :: 2.7
Classifier: Programming Language :: Python :: 3
Classifier: Programming Language :: Python :: 3.4
Classifier: Programming Language :: Python :: 3.5
Classifier: Topic :: Software Development :: Libraries
